rlib/__init__.py
rlib/algorithms/__init__.py
rlib/algorithms/base.py
rlib/algorithms/a2c/__init__.py
rlib/algorithms/a2c/agent.py
rlib/algorithms/a3c/__init__.py
rlib/algorithms/a3c/agent.py
rlib/algorithms/ddpg/__init__.py
rlib/algorithms/ddpg/agent.py
rlib/algorithms/ddpg/model.py
rlib/algorithms/dqn/__init__.py
rlib/algorithms/dqn/agent.py
rlib/algorithms/dqn/model.py
rlib/algorithms/maddpg/__init__.py
rlib/algorithms/maddpg/agent.py
rlib/algorithms/maddpg/model.py
rlib/algorithms/ppo/__init__.py
rlib/algorithms/ppo/agent.py
rlib/algorithms/ppo/model.py
rlib/algorithms/sac/__init__.py
rlib/algorithms/sac/agent.py
rlib/algorithms/td3/__init__.py
rlib/algorithms/td3/agent.py
rlib/algorithms/trpo/__init__.py
rlib/algorithms/trpo/agent.py
rlib/algorithms/vpg/__init__.py
rlib/algorithms/vpg/agent.py
rlib/algorithms/vpg/model.py
rlib/environments/__init__.py
rlib/environments/base.py
rlib/environments/gym.py
rlib/environments/parallel_env.py
rlib/environments/unity.py
rlib/shared/__init__.py
rlib/shared/noise.py
rlib/shared/replay_buffer.py
rlib/shared/utils.py
test/__init__.py
test/algorithms/__init__.py
test/algorithms/ddpg_test.py
test/algorithms/dqn_test.py
test/algorithms/vpg_test.py
test/environments/__init__.py
test/environments/test_base.py
test/environments/test_gym.py
test/environments/test_unity.py
test/shared/__init__.py
test/shared/test_noise.py
test/shared/test_replay_buffer.py
test/shared/test_units.py
rlib-0.0.2.dist-info/LICENSE.md
rlib-0.0.2.dist-info/METADATA
rlib-0.0.2.dist-info/WHEEL
rlib-0.0.2.dist-info/top_level.txt
rlib-0.0.2.dist-info/RECORD
