Metadata-Version: 2.1
Name: rlib
Version: 0.0.2
Summary: Implementations of popular Deep Reinforcement Learning algorithms
Home-page: https://github.com/MarcioPorto/rlib
Author: Márcio Porto
Author-email: mflporto@gmail.com
License: UNKNOWN
Platform: UNKNOWN
Classifier: Programming Language :: Python :: 3
Classifier: License :: OSI Approved :: MIT License
Classifier: Operating System :: OS Independent
